[{"definition":"have offspring or produce more individuals of a given animal or plant; \"The Bible tells people to procreate\"; \"These bacteria reproduce\"","examples":[],"lemmas":[{"lemma":"procreate","language":"en","forms":[],"sense_key":"procreate%2:29:00::","subcats":["The banks %s the check"],"importance":1},{"lemma":"reproduce","language":"en","forms":[],"sense_key":"reproduce%2:29:00::","subcats":["The banks %s the check","The coins %s "],"importance":1},{"lemma":"multiply","language":"en","forms":["multiplied"],"sense_key":"multiply%2:29:01::","subcats":["The banks %s the check","The children %s to the playground","The coins %s ","They %s the car down the avenue"],"importance":1}],"id":"00054856-v","ili":"i22048","pos":"v","subject":"verb.body","relations":[{"src_word":"procreate","trg_word":"procreative","rel_type":"derivation","target":"01085280-s"},{"src_word":"procreate","trg_word":"procreation","rel_type":"derivation","target":"00851153-n"},{"src_word":"reproduce","trg_word":"reproductive","rel_type":"derivation","target":"01085280-s"},{"src_word":"reproduce","trg_word":"reproduction","rel_type":"derivation","target":"13571521-n"},{"src_word":"reproduce","trg_word":"reproduction","rel_type":"derivation","target":"00851153-n"},{"src_word":"multiply","trg_word":"multiplication","rel_type":"derivation","target":"00851612-n"},{"src_word":null,"trg_word":null,"rel_type":"hypernym","target":"01620211-v"},{"src_word":null,"trg_word":null,"rel_type":"domain_topic","target":"06047178-n"},{"src_word":null,"trg_word":null,"rel_type":"hyponym","target":"00055281-v"},{"src_word":null,"trg_word":null,"rel_type":"hyponym","target":"00055930-v"},{"src_word":null,"trg_word":null,"rel_type":"hyponym","target":"00056076-v"},{"src_word":null,"trg_word":null,"rel_type":"hyponym","target":"00059956-v"}],"old_keys":{"pwn20":["00053313-v"],"pwn30":["00055142-v"],"pwn16":["00038872-v"],"pwn21":["00054376-v"],"pwn15":["00035058-v"],"pwn171":["00043825-v"],"pwn17":["00041162-v"]},"gloss":null,"foreign":{"spa":["multiplicarse","procrear","reproducir","reproducirse"],"por":["gerar","procriar","reproduzir"],"hrv":["množiti se","ploditi se","rasploditi se","rasplođivati se","razmnožavati se","razmnožiti se","reproducirati se"],"zsm":["beranak","berlipat ganda","membiak","membiakkan","mengembangbiakkan","menggandakan"],"eus":["ugaldu"],"tha":["สืบพันธุ์"],"fra":["procréer"],"nld":["reproduceren","vermenigvuldigen","voortpanten","voortplanten"],"arb":["أنتج","أنتج ثانية","أنْجب","أنْسل","إستنسخ ثانية","إستنطق الاسطوانة","ازداد","انتشر","تضاعف","تكاثر","تناسل","تواجد","توالد","حدث مرة ثانية","ضاعف","ضرب","كثر","نسخ","وَلَدَ"],"ind":["beranak","berkembang biak","berlipat ganda","membiak","membiakkan","mengembangbiakkan","menggandakan"],"fin":["jatkaa sukua","lisääntyä"],"als":["pjell","riprodhim","shumëfishoj"],"slk":["množiť","množiť sa","plodiť","rozmnožiť sa","rozmnožovať sa","splodiť"],"ita":["moltiplicarsi","procreare","riprodursi"],"slv":["ploditi se","razmnoževati se","razplojevati se","reproducirati se"],"jpn":["増える","殖える"],"ron":["[se] reproduce","[se] înmulți","procrea"],"cat":["procrear","reproduir","reproduir-se"],"ell":["αναπαράγω","πολλαπλασιάζομαι","τεκνοποιώ"]},"links":[{"link_type":"VerbNet","target":"other_cos-45.4"},{"link_type":"W3C","target":"http://www.w3.org/2006/03/wn/wn20/instances/synset-reproduce-verb-2"}]}]