[{"definition":"evolve so as to lead to a new species or develop in a way most suited to the environment","examples":[],"lemmas":[{"lemma":"speciate","language":"en","forms":[],"sense_key":"speciate%2:30:00::","subcats":["The children %s to the playground","The banks %s the check"],"importance":1},{"lemma":"specialise","language":"en","forms":[],"sense_key":"specialise%2:30:07::","subcats":["They %s the car down the avenue","The coins %s ","The men %s the horses across the field","The banks %s the check","They %s up the hill","The children %s the ball","The children %s to the playground"],"importance":1},{"lemma":"specialize","language":"en","forms":[],"sense_key":"specialize%2:30:07::","subcats":["They %s the car down the avenue","The coins %s ","The men %s the horses across the field","The banks %s the check","They %s up the hill","The children %s the ball","The children %s to the playground"],"importance":1},{"lemma":"differentiate","language":"en","forms":[],"sense_key":"differentiate%2:30:05::","subcats":["They %s the car down the avenue","The coins %s ","The ropes %s","The banks %s the check","The cars %s down the avenue","They %s the coin ","The children %s to the playground"],"importance":2}],"id":"00119074-v","ili":"i22355","pos":"v","subject":"verb.change","relations":[{"src_word":"speciate","trg_word":"speciation","rel_type":"derivation","target":"13581282-n"},{"src_word":"specialise","trg_word":"specialisation","rel_type":"derivation","target":"13580985-n"},{"src_word":"specialize","trg_word":"specialization","rel_type":"derivation","target":"13580985-n"},{"src_word":null,"trg_word":null,"rel_type":"hypernym","target":"00251950-v"}],"old_keys":{"pwn30":["00119266-v"],"pwn21":["00117000-v"],"pwn171":["00092139-v"],"pwn20":["00114681-v"]},"gloss":null,"foreign":{"fra":["différencier","dériver"],"ind":["membedakan","mengahlikan"],"jpn":["種分化+する"],"zsm":["mengahlikan"],"fin":["erikoistua","erilaistua","lajiutua"],"tha":["กลายพันธุ์"]},"links":[{"link_type":"W3C","target":"http://www.w3.org/2006/03/wn/wn20/instances/synset-speciate-verb-1"}]}]