[{"definition":"presenting favorable circumstances; likely to result in or show signs of success; \"propitious omens\"; \"propitious gales speeded us along\"; \"a propitious alignment of planets for space exploration\"","examples":[],"lemmas":[{"lemma":"propitious","language":"en","forms":[],"sense_key":"propitious%3:00:00::","subcats":[],"importance":1}],"id":"00178468-a","ili":"i956","pos":"a","subject":"adj.all","relations":[{"src_word":"propitious","trg_word":"propitiousness","rel_type":"derivation","target":"05168623-n"},{"src_word":"propitious","trg_word":"unpropitious","rel_type":"antonym","target":"00179263-a"},{"src_word":null,"trg_word":null,"rel_type":"also","target":"00177411-a"},{"src_word":null,"trg_word":null,"rel_type":"also","target":"00998466-a"},{"src_word":null,"trg_word":null,"rel_type":"attribute","target":"05168623-n"},{"src_word":null,"trg_word":null,"rel_type":"similar","target":"00178829-s"},{"src_word":null,"trg_word":null,"rel_type":"similar","target":"00179134-s"}],"old_keys":{"pwn17":["00179904-a"],"pwn15":["00144193-a"],"pwn30":["00177186-a"],"pwn16":["00177964-a"],"pwn20":["00181655-a"],"pwn21":["00197646-a"],"pwn171":["00179290-a"]},"gloss":null,"foreign":{"glg":["favorable","favorábel","propicio"],"slv":["povoljen","ugoden"],"fin":["suotuisa"],"fra":["bon","propice"],"fas":["مساعد"],"cat":["propici"],"spa":["propicio"],"ita":["fasto","fausto","favorevole","propizio"],"por":["propício"],"swe":["gynnsam"]},"links":[{"link_type":"W3C","target":"http://www.w3.org/2006/03/wn/wn20/instances/synset-propitious-adjective-1"}]}]