[{"definition":"showing disapproval; in a disparaging way; \"he reviewed the play unfavorably\"","examples":[],"lemmas":[{"lemma":"unfavourably","language":"en","forms":[],"sense_key":"unfavourably%4:02:00::","subcats":[],"importance":1},{"lemma":"unfavorably","language":"en","forms":[],"sense_key":"unfavorably%4:02:00::","subcats":[],"importance":1}],"id":"00232197-r","ili":"i19727","pos":"r","subject":"adv.all","relations":[{"src_word":"unfavorably","trg_word":"favorably","rel_type":"antonym","target":"00232060-r"},{"src_word":"unfavorably","trg_word":"unfavorable","rel_type":"derivation","target":"00999867-a"}],"old_keys":{"pwn15":["00150726-r"],"pwn21":["00232202-r"],"pwn20":["00233503-r"],"pwn16":["00227009-r"],"pwn30":["00230581-r"],"pwn171":["00230198-r"],"pwn17":["00228940-r"]},"gloss":null,"foreign":{"ron":["nefavorabil"],"fin":["kielteisesti"],"por":["desfavoravelmente","inconvenientemente"],"fra":["défavorablement"],"jpn":["悪し様に"]},"links":[{"link_type":"W3C","target":"http://www.w3.org/2006/03/wn/wn20/instances/synset-unfavorably-adverb-1"}]}]