[{"definition":"in an impartially dispassionate manner; \"although he was looking at the other girl, he did so dispassionately\"","examples":[],"lemmas":[{"lemma":"dispassionately","language":"en","forms":[],"sense_key":"dispassionately%4:02:00::","subcats":[],"importance":1}],"id":"00318783-r","ili":"i20333","pos":"r","subject":"adv.all","relations":[{"src_word":"dispassionately","trg_word":"dispassionate","rel_type":"derivation","target":"01727865-s"}],"old_keys":{"pwn17":["00314776-r"],"pwn21":["00319593-r"],"pwn30":["00317390-r"],"pwn171":["00316465-r"],"pwn15":["00217377-r"],"pwn20":["00320749-r"],"pwn16":["00312111-r"]},"gloss":null,"foreign":{"fra":["impassiblement"],"fin":["kiihkottomasti","tyynesti"],"ita":["serenamente","spassionatamente"],"ron":["imperturbabil"],"por":["friamente","insensivelmente"],"tha":["อย่างสงบ"],"jpn":["冷静に"]},"links":[{"link_type":"W3C","target":"http://www.w3.org/2006/03/wn/wn20/instances/synset-dispassionately-adverb-1"}]}]