[{"definition":"amplify (an electron current) by causing part of the power in the output circuit to act upon the input circuit","examples":[],"lemmas":[{"lemma":"regenerate","language":"en","forms":[],"sense_key":"regenerate%2:30:06::","subcats":["They %s the car down the avenue","The coins %s ","The banks %s the check","The cars %s down the avenue","They %s the coin ","The children %s to the playground"],"importance":8}],"id":"00385860-v","ili":"i23658","pos":"v","subject":"verb.change","relations":[{"src_word":"regenerate","trg_word":"regeneration","rel_type":"derivation","target":"13560465-n"},{"src_word":null,"trg_word":null,"rel_type":"hypernym","target":"00153083-v"}],"old_keys":{"pwn21":["00381157-v"],"pwn16":["00267871-v"],"pwn20":["00373585-v"],"pwn171":["00308554-v"],"pwn15":["00230177-v"],"pwn30":["00385189-v"],"pwn17":["00288284-v"]},"gloss":null,"foreign":{"fin":["regeneroida"],"cmn":["加压","增压"],"fra":["régénérer"],"ron":["amplifica"],"por":["regenerar"],"cat":["regenerar"]},"links":[{"link_type":"W3C","target":"http://www.w3.org/2006/03/wn/wn20/instances/synset-regenerate-verb-2"}]}]