[{"definition":"with jealousy; \"he guarded his privacy jealously\"","examples":[],"lemmas":[{"lemma":"jealously","language":"en","forms":[],"sense_key":"jealously%4:02:00::","subcats":[],"importance":2}],"id":"00385526-r","ili":"i20771","pos":"r","subject":"adv.all","relations":[{"src_word":"jealously","trg_word":"jealous","rel_type":"derivation","target":"00892058-s"}],"old_keys":{"pwn16":["00378612-r"],"pwn171":["00383310-r"],"pwn20":["00387750-r"],"pwn21":["00385876-r"],"pwn30":["00383693-r"],"pwn17":["00381580-r"],"pwn15":["00273634-r"]},"gloss":null,"foreign":{"cmn":["妒忌+地","猜疑+地"],"ita":["gelosamente"],"spa":["celosamente"],"ron":["gelos"],"fin":["mustasukkaisesti"],"tha":["อย่างหึงหวง"],"fra":["envieusement","jalousement"]},"links":[{"link_type":"W3C","target":"http://www.w3.org/2006/03/wn/wn20/instances/synset-jealously-adverb-1"}]}]