[{"definition":"in a miserable manner; \"I bit my lip miserably and nodded\"","examples":[],"lemmas":[{"lemma":"miserably","language":"en","forms":[],"sense_key":"miserably%4:02:00::","subcats":[],"importance":1}],"id":"00404848-r","ili":"i20904","pos":"r","subject":"adv.all","relations":[{"src_word":"miserably","trg_word":"miserable","rel_type":"derivation","target":"00480862-s"}],"old_keys":{"pwn30":["00402938-r"],"pwn21":["00405238-r"],"pwn17":["00400552-r"],"pwn15":["00289541-r"],"pwn20":["00406888-r"],"pwn171":["00402292-r"],"pwn16":["00397497-r"]},"gloss":null,"foreign":{"ita":["miseramente"],"fra":["lamentablement","misérablement"],"tha":["อย่างเป็นทุกข์"],"slv":["nesrečno"],"jpn":["みじめに","悲惨に"],"por":["miseravelmente","miseràvel"],"fin":["surkeasti"],"cmn":["可哀+地","可悲+地","悲惨+地","糟糕+地","贫困+地","非常不幸+地"]},"links":[{"link_type":"W3C","target":"http://www.w3.org/2006/03/wn/wn20/instances/synset-miserably-adverb-1"}]}]