[{"definition":"the sport of racing greyhounds","examples":[],"lemmas":[{"lemma":"greyhound racing","language":"en","forms":[],"sense_key":"greyhound_racing%1:04:00::","subcats":[],"importance":1}],"id":"00450962-n","ili":"i37774","pos":"n","subject":"noun.act","relations":[{"src_word":null,"trg_word":null,"rel_type":"hypernym","target":"00450280-n"}],"old_keys":{"pwn15":["00250413-n"],"pwn16":["00285301-n"],"pwn21":["00445296-n"],"pwn171":["00336325-n"],"pwn20":["00426268-n"],"pwn30":["00449977-n"],"pwn17":["00317607-n"]},"gloss":null,"foreign":{"fin":["vinttikoirakilpailu"],"tha":["การวิ่งแข่งของสุนัขเกรย์เฮานด์"],"spa":["carrera de galgos"],"fra":["course de lévriers"],"ron":["cursădeogari"],"cat":["carrera de llebrers"]},"links":[{"link_type":"W3C","target":"http://www.w3.org/2006/03/wn/wn20/instances/synset-greyhound_racing-noun-1"}]}]