[{"definition":"remove from a contest or race; \"The cyclist has eliminated all the competitors in the race\"","examples":[],"lemmas":[{"lemma":"eliminate","language":"en","forms":[],"sense_key":"eliminate%2:33:00::","subcats":["The coins %s ","They %s the coin ","The cars %s down the avenue","They %s the car down the avenue"],"importance":6}],"id":"01105250-v","ili":"i27105","pos":"v","subject":"verb.competition","relations":[{"src_word":null,"trg_word":null,"rel_type":"hypernym","target":"01104324-v"}],"old_keys":{"pwn171":["00869231-v"],"pwn30":["01102839-v"],"pwn21":["01091895-v"],"pwn20":["01067698-v"]},"gloss":null,"foreign":{"slv":["odstraniti"],"fra":["supprimer","éliminer"],"ron":["elimina","scoate"],"zsm":["membersihkan","membuangkan","mengeluarkan","mengganyang","menyingkirkan"],"tha":["กีดกัน"],"ind":["membersihkan","membuangkan","mengeluarkan","mengganyang","menyingkirkan"],"fin":["eliminoida"]},"links":[{"link_type":"W3C","target":"http://www.w3.org/2006/03/wn/wn20/instances/synset-eliminate-verb-6"}]}]