[{"definition":"seek, search for; \"She hunted for her reading glasses but was unable to locate them\"","examples":[],"lemmas":[{"lemma":"hunt","language":"en","forms":[],"sense_key":"hunt%2:35:03::","subcats":["The coins %s ","The banks %s the check","The cars %s down the avenue","They %s the coin ","The children %s to the playground"],"importance":3}],"id":"01319061-v","ili":"i28265","pos":"v","subject":"verb.contact","relations":[{"src_word":"hunt","trg_word":"hunt","rel_type":"derivation","target":"05778254-n"},{"src_word":"hunt","trg_word":"hunt","rel_type":"derivation","target":"00947217-n"},{"src_word":"hunt","trg_word":"hunter","rel_type":"derivation","target":"10213338-n"},{"src_word":"hunt","trg_word":"hunting","rel_type":"derivation","target":"00947217-n"},{"src_word":null,"trg_word":null,"rel_type":"hypernym","target":"01318273-v"}],"old_keys":{"pwn21":["01304787-v"],"pwn171":["01041332-v"],"pwn20":["01277348-v"],"pwn17":["00975682-v"],"pwn30":["01316401-v"]},"gloss":null,"foreign":{"fin":["etsiä"],"ron":["dacupușca"],"slv":["loviti"],"fra":["chasse","chasser","rechercher"],"tha":["ตามล่า","ล่าตัว"],"spa":["buscar","cazar","rastrear"]},"links":[{"link_type":"VerbNet","target":"hunt-35.1"},{"link_type":"W3C","target":"http://www.w3.org/2006/03/wn/wn20/instances/synset-hunt-verb-6"}]}]