[{"definition":"fail to function or function improperly; \"the coffee maker malfunctioned\"","examples":[],"lemmas":[{"lemma":"malfunction","language":"en","forms":[],"sense_key":"malfunction%2:35:00::","subcats":["The children %s to the playground"],"importance":1},{"lemma":"misfunction","language":"en","forms":[],"sense_key":"misfunction%2:35:00::","subcats":["The children %s to the playground"],"importance":1}],"id":"01528083-v","ili":"i29356","pos":"v","subject":"verb.contact","relations":[{"src_word":"malfunction","trg_word":"malfunction","rel_type":"derivation","target":"07333076-n"},{"src_word":"malfunction","trg_word":"function","rel_type":"antonym","target":"01528454-v"},{"src_word":null,"trg_word":null,"rel_type":"hypernym","target":"00435327-v"},{"src_word":null,"trg_word":null,"rel_type":"hyponym","target":"01527965-v"}],"old_keys":{"pwn16":["01048560-v"],"pwn30":["01525295-v"],"pwn20":["01483014-v"],"pwn21":["01512451-v"],"pwn171":["01207920-v"],"pwn17":["01138008-v"],"pwn15":["00877378-v"]},"gloss":null,"foreign":{"qcn":["病"],"por":["enguiçar"],"fin":["toimia huonosti"],"ell":["δυσλειτουργώ"],"slk":["nefungovať","vypovedať činnosť","zlyhať"],"fra":["fonctionner"],"hrv":["ne funkcionirati","ne raditi ispravno"]},"links":[{"link_type":"W3C","target":"http://www.w3.org/2006/03/wn/wn20/instances/synset-malfunction-verb-1"}]}]