[{"definition":"carry out or perform an action; \"John did the painting, the weeding, and he cleaned out the gutters\"; \"the skater executed a triple pirouette\"; \"she did a little dance\"","examples":[],"lemmas":[{"lemma":"perform","language":"en","forms":[],"sense_key":"perform%2:36:00::","subcats":["The coins %s ","The banks %s the check","The men %s the horses across the field","They %s the coin "],"importance":1},{"lemma":"execute","language":"en","forms":[],"sense_key":"execute%2:36:01::","subcats":["The coins %s ","They %s the coin ","They %s the car down the avenue"],"importance":3},{"lemma":"do","language":"en","forms":["did","done"],"sense_key":"do%2:36:01::","subcats":["They %s the car down the avenue","The coins %s ","The men %s the horses across the field","The banks %s the check","The wooden sticks %s ","They %s the bags on the table","They %s the people the food","The children %s the ball","The girls %s the wooden sticks","They %s the coin ","The children %s to the playground"],"importance":5}],"id":"01716563-v","ili":"i30309","pos":"v","subject":"verb.creation","relations":[{"src_word":"perform","trg_word":"performance","rel_type":"derivation","target":"00098324-n"},{"src_word":"execute","trg_word":"execution","rel_type":"derivation","target":"00098324-n"},{"src_word":"execute","trg_word":"executant","rel_type":"derivation","target":"10089103-n"},{"src_word":"do","trg_word":"doer","rel_type":"derivation","target":"09786620-n"},{"src_word":null,"trg_word":null,"rel_type":"hyponym","target":"00492487-v"},{"src_word":null,"trg_word":null,"rel_type":"hyponym","target":"01051478-v"},{"src_word":null,"trg_word":null,"rel_type":"hyponym","target":"01052437-v"},{"src_word":null,"trg_word":null,"rel_type":"hyponym","target":"01053236-v"},{"src_word":null,"trg_word":null,"rel_type":"hyponym","target":"01707716-v"},{"src_word":null,"trg_word":null,"rel_type":"hyponym","target":"01716413-v"},{"src_word":null,"trg_word":null,"rel_type":"hyponym","target":"01717207-v"},{"src_word":null,"trg_word":null,"rel_type":"hyponym","target":"01717350-v"},{"src_word":null,"trg_word":null,"rel_type":"hyponym","target":"01717446-v"},{"src_word":null,"trg_word":null,"rel_type":"hyponym","target":"01717842-v"},{"src_word":null,"trg_word":null,"rel_type":"hyponym","target":"01717954-v"},{"src_word":null,"trg_word":null,"rel_type":"hyponym","target":"01722044-v"},{"src_word":null,"trg_word":null,"rel_type":"hyponym","target":"01724857-v"},{"src_word":null,"trg_word":null,"rel_type":"hyponym","target":"01725046-v"},{"src_word":null,"trg_word":null,"rel_type":"hyponym","target":"01727101-v"},{"src_word":null,"trg_word":null,"rel_type":"hyponym","target":"01732719-v"},{"src_word":null,"trg_word":null,"rel_type":"hyponym","target":"01736053-v"},{"src_word":null,"trg_word":null,"rel_type":"hyponym","target":"01736802-v"},{"src_word":null,"trg_word":null,"rel_type":"hyponym","target":"01759660-v"}],"old_keys":{"pwn21":["01697549-v"],"pwn16":["01173875-v"],"pwn17":["01274998-v"],"pwn20":["01663763-v"],"pwn171":["01349386-v"],"pwn30":["01712704-v"]},"gloss":null,"foreign":{"ell":["εκτελώ"],"cat":["dur a terme","executar","fer"],"fra":["accomplir","effectuer","exécuter","faire","réaliser"],"als":["bëj","ekzekutoj","kryej"],"slk":["robiť","spraviť","urobiť","vykonať","vykonávať","vystupovať (na verejnosti)","vystúpiť (na verejnosti)"],"slv":["delati","izvajati","izvesti","izvršiti","napraviti","narediti","opraviti","opravljati","storiti"],"hrv":["izvesti","izvoditi","izvršavati","izvršiti","napraviti","obaviti","obavljati","odrađivati","počiniti","praviti","učiniti","činiti"],"ron":["efectua","executa","face","realiza"],"ita":["eseguire","fare"],"fin":["esittää","suorittaa","tehdä"],"zsm":["berbuat","buat","melaksanakan","melakukan","melangsungkan","memainkan","membuat","mempertontonkan","mempertunjukkan","mengakok","menjalankan","menyelenggarakan"],"glg":["executar","facer"],"ind":["berbuat","buat","melaksanakan","melakukan","melangsungkan","memainkan","membuat","mempertontonkan","mempertunjukkan","mengakok","menjalankan","menyelenggarakan"],"arb":["أدى","أعد للطبخ","أعدم","أنتج","أنهى","احتال","ارتكب","انتهى","اهتم","بذل","جرى","جرى ما هو ضرورى","جمل بمستحضرات تجميل","خدع","رتب","رقص","زخرف","عزف","غنى","فعل","قام ب","قدم خدمة","قضى","مارس","مثل","مثل دور في مسرحية","نجز","نظف","نفذ","نفّد","وضع"],"spa":["ejecutar","hacer"],"nld":["doen","uitvoeren"],"eus":["bete","burutu","egin","gauzatu"],"qcn":["下","付諸","使","來","施","演出","耍"],"tha":["แสดง"],"jpn":["し遂げる","する","でかす","とり熟す","とり行う","やらかす","やる","仕出かす","仕出来す","出かす","出来す","取りこなす","取り熟す","取熟す","執り行う","執り行なう","執行+する","執行う","執行なう","実施+する","実行+する","実践+する","履行+する","成しとげる","成し遂げる","成す","果す","為す","為る","為出かす","為出来す","致す","行う","行ずる","行なう","遂げる","遂行+する","達成+する","遣らかす","遣り遂げる","遣る"],"por":["executar","fazer"]},"links":[{"link_type":"W3C","target":"http://www.w3.org/2006/03/wn/wn20/instances/synset-perform-verb-1"}]}]