[{"definition":"markings vary but usually harmonize with background; of southwestern Arizona and Baja California","examples":[],"lemmas":[{"lemma":"speckled rattlesnake","language":"en","forms":[],"sense_key":"speckled_rattlesnake%1:05:00::","subcats":[],"importance":1},{"lemma":"Crotalus mitchellii","language":"en","forms":[],"sense_key":"crotalus_mitchellii%1:05:00::","subcats":[],"importance":1}],"id":"01759984-n","ili":"i44565","pos":"n","subject":"noun.animal","relations":[{"src_word":null,"trg_word":null,"rel_type":"hypernym","target":"01757517-n"},{"src_word":null,"trg_word":null,"rel_type":"holo_member","target":"01757915-n"}],"old_keys":{"pwn30":["01757343-n"],"pwn15":["01117225-n"],"pwn20":["01678080-n"],"pwn16":["01277441-n"],"pwn21":["01738780-n"],"pwn17":["01382056-n"],"pwn171":["01432604-n"]},"gloss":null,"foreign":{"fra":["crotale tacheté"],"pol":["grzechotnik kropiaty"],"fin":["Crotalus mitchellii","kalkkarokäärme"]},"links":[{"link_type":"W3C","target":"http://www.w3.org/2006/03/wn/wn20/instances/synset-speckled_rattlesnake-noun-1"}]}]