[{"definition":"of or relating to clergy bound by monastic vows; \"the religious or regular clergy conducts the service\"","examples":[],"lemmas":[{"lemma":"religious","language":"en","forms":[],"sense_key":"religious%3:00:01::","subcats":[],"importance":1}],"id":"01787508-a","ili":"i9782","pos":"a","subject":"adj.all","relations":[{"src_word":"religious","trg_word":"religious","rel_type":"derivation","target":"10538195-n"},{"src_word":"religious","trg_word":"secular","rel_type":"antonym","target":"01787381-a"}],"old_keys":{"pwn15":["02127427-a"],"pwn30":["01782981-a"]},"gloss":null,"foreign":{"glg":["relixioso"],"fra":["religieux"],"fin":["kirkollinen"]},"links":[]}]