[{"definition":"set afloat again; \"refloat a grounded boat\"","examples":[],"lemmas":[{"lemma":"refloat","language":"en","forms":[],"sense_key":"refloat%2:38:00::","subcats":["The coins %s "],"importance":1}],"id":"01879029-v","ili":"i31082","pos":"v","subject":"verb.motion","relations":[{"src_word":null,"trg_word":null,"rel_type":"hypernym","target":"01878561-v"}],"old_keys":{"pwn20":["01820924-v"],"pwn16":["01280919-v"],"pwn171":["01474977-v"],"pwn15":["01069324-v"],"pwn30":["01875036-v"],"pwn21":["01857447-v"],"pwn17":["01394912-v"]},"gloss":null,"foreign":{"ita":["disincagliare"],"jpn":["離礁+する"],"fin":["asettaa kellumaan"],"tha":["ลอยใหม่"]},"links":[{"link_type":"W3C","target":"http://www.w3.org/2006/03/wn/wn20/instances/synset-refloat-verb-1"}]}]