[{"definition":"of or relating to the armpit; \"axillary gland\"","examples":[],"lemmas":[{"lemma":"axillary","language":"en","forms":[],"sense_key":"axillary%3:01:01::","subcats":[],"importance":1}],"id":"02665885-a","ili":"i14826","pos":"a","subject":"adj.pert","relations":[{"src_word":"axillary","trg_word":"axilla","rel_type":"derivation","target":"05557209-n"},{"src_word":"axillary","trg_word":"armpit","rel_type":"pertainym","target":"05557209-n"},{"src_word":null,"trg_word":null,"rel_type":"domain_topic","target":"06067070-n"}],"old_keys":{"pwn20":["02554404-a"],"pwn21":["02741780-a"],"pwn16":["02514721-a"],"pwn171":["02564561-a"],"pwn15":["01993308-a"],"pwn30":["02655180-a"],"pwn17":["02561264-a"]},"gloss":null,"foreign":{"fin":["kainalo-","kainalon"],"pol":["pachowy"],"spa":["axilar","de la axila","del sobaco"],"cmn":["腋窝+的"],"cat":["axil·lar"]},"links":[{"link_type":"W3C","target":"http://www.w3.org/2006/03/wn/wn20/instances/synset-axillary-adjective-2"}]}]