[{"definition":"any wall supporting a floor or the roof of a building","examples":[],"lemmas":[{"lemma":"bearing wall","language":"en","forms":[],"sense_key":"bearing_wall%1:06:00::","subcats":[],"importance":1}],"id":"02820521-n","ili":"i50625","pos":"n","subject":"noun.artifact","relations":[{"src_word":null,"trg_word":null,"rel_type":"hypernym","target":"04554141-n"},{"src_word":null,"trg_word":null,"rel_type":"hypernym","target":"04366676-n"}],"old_keys":{"pwn20":["02718426-n"],"pwn21":["02790538-n"],"pwn30":["02817386-n"],"pwn15":["03150309-n"],"pwn17":["02395853-n"],"pwn16":["02272174-n"],"pwn171":["02450749-n"]},"gloss":null,"foreign":{"fin":["kantava seinä"],"ron":["peretederezistență"],"cmn":["承重墙"],"nld":["draagmuur","steunmuur"]},"links":[{"link_type":"W3C","target":"http://www.w3.org/2006/03/wn/wn20/instances/synset-bearing_wall-noun-1"}]}]