[{"definition":"of or relating to the ancient Greek inhabitants of Doris, to their Doric dialect of Greek, or to their culture","examples":[],"lemmas":[{"lemma":"Dorian","language":"en","forms":[],"sense_key":"dorian%3:01:00::","subcats":[],"importance":1}],"id":"02858092-a","ili":"i16167","pos":"a","subject":"adj.pert","relations":[{"src_word":"Dorian","trg_word":"Doris","rel_type":"pertainym","target":"08801296-n"}],"old_keys":{"pwn30":["02847207-a"]},"gloss":null,"foreign":{"por":["dórica"],"fin":["doorilainen"],"tha":["โดเรียน"]},"links":[]}]