[{"definition":"a wrench designed to provide a firm grip on something","examples":[],"lemmas":[{"lemma":"bulldog wrench","language":"en","forms":[],"sense_key":"bulldog_wrench%1:06:00::","subcats":[],"importance":1}],"id":"02919411-n","ili":"i51230","pos":"n","subject":"noun.artifact","relations":[{"src_word":null,"trg_word":null,"rel_type":"hypernym","target":"04613932-n"}],"old_keys":{"pwn20":["02812249-n"],"pwn15":["02210502-n"],"pwn17":["02480625-n"],"pwn21":["02887661-n"],"pwn30":["02916065-n"],"pwn16":["02350287-n"],"pwn171":["02536201-n"]},"gloss":null,"foreign":{"fin":["jakoavain"],"cmn":["管子扳手"]},"links":[{"link_type":"W3C","target":"http://www.w3.org/2006/03/wn/wn20/instances/synset-bulldog_wrench-noun-1"}]}]