[{"definition":"a cephalosporin antibiotic (trade name Ultracef)","examples":[],"lemmas":[{"lemma":"Ultracef","language":"en","forms":[],"sense_key":"ultracef%1:06:00::","subcats":[],"importance":1},{"lemma":"cefadroxil","language":"en","forms":[],"sense_key":"cefadroxil%1:06:00::","subcats":[],"importance":1}],"id":"02992633-n","ili":"i51677","pos":"n","subject":"noun.artifact","relations":[{"src_word":"Ultracef","trg_word":"trade name","rel_type":"exemplifies","target":"06858649-n"},{"src_word":null,"trg_word":null,"rel_type":"hypernym","target":"03000447-n"}],"old_keys":{"pwn17":["02546155-n"],"pwn30":["02989178-n"],"pwn20":["02882714-n"],"pwn171":["02602254-n"],"pwn21":["02960166-n"]},"gloss":null,"foreign":{"jpn":["セファドロキシル"],"fin":["Ultracef","kefadroksiili"],"cmn":["头孢羟胺苄"],"spa":["Ultracef","cefadroxilo"],"por":["cefadroxil"],"tha":["เซฟาดรอกซิล"]},"links":[{"link_type":"W3C","target":"http://www.w3.org/2006/03/wn/wn20/instances/synset-cefadroxil-noun-1"}]}]