[{"definition":"an apparatus for holding substances that are undergoing a chemical reaction","examples":[],"lemmas":[{"lemma":"chemical reactor","language":"en","forms":[],"sense_key":"chemical_reactor%1:06:00::","subcats":[],"importance":1}],"id":"03016660-n","ili":"i51818","pos":"n","subject":"noun.artifact","relations":[{"src_word":null,"trg_word":null,"rel_type":"hypernym","target":"02730750-n"},{"src_word":null,"trg_word":null,"rel_type":"hyponym","target":"02985024-n"}],"old_keys":{"pwn15":["02491212-n"],"pwn171":["02622914-n"],"pwn20":["02904920-n"],"pwn17":["02566190-n"],"pwn21":["02983055-n"],"pwn30":["03013006-n"],"pwn16":["02426337-n"]},"gloss":null,"foreign":{"tha":["เครื่องปฏิกรณ์เคมี"],"fin":["kemiallinen reaktori"],"cmn":["化学反应器"],"fra":["réacteur","réacteur chimique"],"por":["Reator químico"]},"links":[{"link_type":"W3C","target":"http://www.w3.org/2006/03/wn/wn20/instances/synset-chemical_reactor-noun-1"}]}]