[{"definition":"of or relating to a directionless magnitude (such as mass or speed etc.) that is completely specified by its magnitude; \"scalar quantity\"","examples":[],"lemmas":[{"lemma":"scalar","language":"en","forms":[],"sense_key":"scalar%3:01:00::","subcats":[],"importance":1}],"id":"03146439-a","ili":"i18005","pos":"a","subject":"adj.pert","relations":[{"src_word":"scalar","trg_word":"scalar","rel_type":"derivation","target":"05872935-n"},{"src_word":"scalar","trg_word":"scale","rel_type":"pertainym","target":"13837554-n"}],"old_keys":{"pwn171":["02954247-a"],"pwn15":["02232190-a"],"pwn20":["02965172-a"],"pwn17":["02947622-a"],"pwn21":["03213290-a"],"pwn16":["02869635-a"],"pwn30":["03134771-a"]},"gloss":null,"foreign":{"ita":["scalare"],"pol":["skalarny"],"por":["escalar"],"fin":["skalaari-"],"cmn":["无向量+的","标量+的"]},"links":[{"link_type":"W3C","target":"http://www.w3.org/2006/03/wn/wn20/instances/synset-scalar-adjective-1"}]}]