[{"definition":"the lower of two berths","examples":[],"lemmas":[{"lemma":"lower berth","language":"en","forms":[],"sense_key":"lower_berth%1:06:00::","subcats":[],"importance":1},{"lemma":"lower","language":"en","forms":[],"sense_key":"lower%1:06:00::","subcats":[],"importance":1}],"id":"03699299-n","ili":"i55848","pos":"n","subject":"noun.artifact","relations":[{"src_word":"lower","trg_word":"lower","rel_type":"derivation","target":"01577754-v"},{"src_word":"lower","trg_word":"lower","rel_type":"derivation","target":"01977139-v"},{"src_word":null,"trg_word":null,"rel_type":"hypernym","target":"02834929-n"}],"old_keys":{"pwn171":["03218012-n"],"pwn30":["03693973-n"],"pwn15":["02152578-n"],"pwn17":["03151880-n"],"pwn20":["03556300-n"],"pwn21":["03653193-n"],"pwn16":["02945137-n"]},"gloss":null,"foreign":{"por":["mais baixo"],"ind":["bawah"],"fas":["پایینتر"],"zsm":["bawah"],"jpn":["下段"],"fin":["alempi","alempi makuupaikka"],"cmn":["下铺"]},"links":[{"link_type":"W3C","target":"http://www.w3.org/2006/03/wn/wn20/instances/synset-lower_berth-noun-1"}]}]