[{"definition":"the basic cognitive process of arranging into classes or categories","examples":[],"lemmas":[{"lemma":"classification","language":"en","forms":[],"sense_key":"classification%1:09:00::","subcats":[],"importance":3},{"lemma":"categorization","language":"en","forms":[],"sense_key":"categorization%1:09:00::","subcats":[],"importance":2},{"lemma":"sorting","language":"en","forms":[],"sense_key":"sorting%1:09:00::","subcats":[],"importance":2},{"lemma":"categorisation","language":"en","forms":[],"sense_key":"categorisation%1:09:00::","subcats":[],"importance":2}],"id":"05740701-n","ili":"i67032","pos":"n","subject":"noun.cognition","relations":[{"src_word":"classification","trg_word":"classify","rel_type":"derivation","target":"00741667-v"},{"src_word":"classification","trg_word":"classify","rel_type":"derivation","target":"00656296-v"},{"src_word":"categorization","trg_word":"categorize","rel_type":"derivation","target":"00658931-v"},{"src_word":null,"trg_word":null,"rel_type":"hypernym","target":"05709891-n"},{"src_word":null,"trg_word":null,"rel_type":"hyponym","target":"05649277-n"},{"src_word":null,"trg_word":null,"rel_type":"hyponym","target":"05741528-n"},{"src_word":null,"trg_word":null,"rel_type":"hyponym","target":"05742504-n"},{"src_word":null,"trg_word":null,"rel_type":"hyponym","target":"05742854-n"},{"src_word":null,"trg_word":null,"rel_type":"hyponym","target":"05743734-n"},{"src_word":null,"trg_word":null,"rel_type":"hyponym","target":"05743947-n"}],"old_keys":{"pwn17":["04825351-n"],"pwn30":["05732756-n"],"pwn16":["04425786-n"],"pwn20":["05400179-n"],"pwn171":["04916095-n"],"pwn15":["03900455-n"],"pwn21":["05662132-n"]},"gloss":null,"foreign":{"ita":["classificazione"],"als":["kategorizoj","klasifikim","klasifikoj"],"eus":["mailaketa","sailkapen"],"slv":["kategorizacija","klasifikacija","razporejanje","razvrščanje","sortiranje"],"lit":["klasifikavimas","rūšiavimas"],"fra":["catégorisation","classement","classification","tri"],"por":["Classificação","categorização","classificação"],"zsm":["klasifikasi","pengasingan","pengelasan","penggolongan","pengisihan"],"arb":["تبْوِيب","ترْتِيب","تصْنِيف","فرْز"],"slk":["kategorizácia","klasifikácia","triedenie"],"heb":["!מִיּוּן"],"tha":["การแบ่งนิวเคลียส"],"glg":["categorización"],"hrv":["kategoriziracija","kategoriziranje","klasificiranje","klasifikacija"],"ell":["κατηγοριοποίηση"],"jpn":["内訳","分類","区分","区分け","区別","格付け","種別","類別"],"cat":["categorització","classificació"],"ron":["categorizare","clasificare"],"spa":["clasificación"],"fin":["lajittelu","luokittelu","luokitus"],"ind":["klasifikasi","pengasingan","pengelasan","penggolongan"]},"links":[{"link_type":"W3C","target":"http://www.w3.org/2006/03/wn/wn20/instances/synset-classification-noun-3"}]}]