[{"definition":"(psychology) unconscious internalization of aspects of the world (especially aspects of persons) within the self in such a way that the internalized representation takes over the psychological functions of the external objects","examples":[],"lemmas":[{"lemma":"introjection","language":"en","forms":[],"sense_key":"introjection%1:09:01::","subcats":[],"importance":1}],"id":"05762194-n","ili":"i67139","pos":"n","subject":"noun.cognition","relations":[{"src_word":"introjection","trg_word":"introject","rel_type":"derivation","target":"00555971-v"},{"src_word":null,"trg_word":null,"rel_type":"hypernym","target":"05761951-n"},{"src_word":null,"trg_word":null,"rel_type":"domain_topic","target":"06145709-n"}],"old_keys":{"pwn30":["05754197-n"],"pwn171":["04934776-n"],"pwn20":["05421260-n"],"pwn21":["05683460-n"],"pwn17":["04843387-n"]},"gloss":null,"foreign":{"spa":["introyección"],"ron":["introiecție"],"pol":["introjekcja"],"fin":["sisäistys"]},"links":[{"link_type":"W3C","target":"http://www.w3.org/2006/03/wn/wn20/instances/synset-introjection-noun-2"}]}]