[{"definition":"edible seeds of various pod-bearing plants (peas or beans or lentils etc.)","examples":[],"lemmas":[{"lemma":"pulse","language":"en","forms":[],"sense_key":"pulse%1:13:00::","subcats":[],"importance":3}],"id":"07724791-n","ili":"i77508","pos":"n","subject":"noun.food","relations":[{"src_word":null,"trg_word":null,"rel_type":"hypernym","target":"07724543-n"}],"old_keys":{"pwn17":["06276117-n"],"pwn30":["07709046-n"],"pwn171":["06419207-n"],"pwn21":["07603538-n"],"pwn15":["04938497-n"],"pwn16":["05748135-n"],"pwn20":["07237367-n"]},"gloss":null,"foreign":{"tha":["เมล็ดพืชที่กินได้"],"jpn":["豆類"],"slv":["utrip"],"cat":["llegum"],"fra":["pouls"],"nld":["peul","peultje"],"eus":["lekale"],"ita":["civaia"],"ind":["buncis","kacang","kacang hijau"],"hrv":["zrnje"],"fin":["palkohedelmä"],"ron":["păstaie"],"zsm":["buncis","kacang","kacang hijau","kekacang"]},"links":[{"link_type":"W3C","target":"http://www.w3.org/2006/03/wn/wn20/instances/synset-pulse-noun-4"}]}]