[{"definition":"a native or inhabitant of Costa Rica","examples":[],"lemmas":[{"lemma":"Costa Rican","language":"en","forms":[],"sense_key":"costa_rican%1:18:00::","subcats":[],"importance":1}],"id":"09718184-n","ili":"i87622","pos":"n","subject":"noun.person","relations":[{"src_word":null,"trg_word":null,"rel_type":"hypernym","target":"09716797-n"},{"src_word":null,"trg_word":null,"rel_type":"holo_member","target":"08753940-n"}],"old_keys":{"pwn171":["07969610-n"],"pwn16":["07011899-n"],"pwn21":["09559071-n"],"pwn17":["07794727-n"],"pwn20":["09086382-n"],"pwn30":["09698788-n"],"pwn15":["05880565-n"]},"gloss":null,"foreign":{"lit":["Kosta Rikos gyventojas"],"ron":["costarican"],"eus":["costarricar"],"ita":["costaricano","costaricense"],"slk":["Kostaričan"],"fin":["costaricalainen"],"fra":["Costaricain"],"tha":["ชาวคอสตาริกา"],"cat":["costa-riqueny"]},"links":[{"link_type":"W3C","target":"http://www.w3.org/2006/03/wn/wn20/instances/synset-Costa_Rican-noun-1"}]}]