[{"definition":"a person who is an assistant or subordinate to another","examples":[],"lemmas":[{"lemma":"adjunct","language":"en","forms":[],"sense_key":"adjunct%1:18:00::","subcats":[],"importance":3}],"id":"09789226-n","ili":"i88078","pos":"n","subject":"noun.person","relations":[{"src_word":"adjunct","trg_word":"adjunct","rel_type":"derivation","target":"00796805-s"},{"src_word":null,"trg_word":null,"rel_type":"hypernym","target":"09836176-n"}],"old_keys":{"pwn16":["07062567-n"],"pwn171":["08028209-n"],"pwn30":["09769803-n"],"pwn15":["05920500-n"],"pwn20":["09150245-n"],"pwn17":["07851078-n"],"pwn21":["09626528-n"]},"gloss":null,"foreign":{"por":["acessória"],"eus":["mendeko"],"nld":["bepaling"],"cmn":["副手","助手"],"zsm":["keterangan","penolong"],"cat":["adjunt"],"ind":["ajudan","keterangan","penolong"],"fas":["معاون","یار"],"fin":["alainen","apu-","apulais-"]},"links":[{"link_type":"W3C","target":"http://www.w3.org/2006/03/wn/wn20/instances/synset-adjunct-noun-2"}]}]