[{"definition":"a person who holds assets in trust for a beneficiary; \"it is illegal for a fiduciary to misappropriate money for personal gain\"","examples":[],"lemmas":[{"lemma":"fiduciary","language":"en","forms":[],"sense_key":"fiduciary%1:18:00::","subcats":[],"importance":1}],"id":"10105843-n","ili":"i89933","pos":"n","subject":"noun.person","relations":[{"src_word":"fiduciary","trg_word":"fiduciary","rel_type":"derivation","target":"02859273-a"},{"src_word":null,"trg_word":null,"rel_type":"hypernym","target":"00007846-n"},{"src_word":null,"trg_word":null,"rel_type":"hyponym","target":"09634752-n"},{"src_word":null,"trg_word":null,"rel_type":"hyponym","target":"09790166-n"},{"src_word":null,"trg_word":null,"rel_type":"hyponym","target":"10090026-n"},{"src_word":null,"trg_word":null,"rel_type":"hyponym","target":"10285229-n"},{"src_word":null,"trg_word":null,"rel_type":"hyponym","target":"10674881-n"},{"src_word":null,"trg_word":null,"rel_type":"hyponym","target":"10751971-n"}],"old_keys":{"pwn171":["08276379-n"],"pwn21":["09936041-n"],"pwn17":["08093649-n"],"pwn30":["10086074-n"],"pwn16":["07261351-n"],"pwn20":["09438856-n"]},"gloss":null,"foreign":{"tha":["ผู้ได้รับมอบอำนาจหรือทรัพย์สิน"],"por":["fiduciário"],"nld":["curator","vertrouwens-","zaakwaarnemer"],"fas":["امانتی"],"jpn":["信義誠実の原則"],"slk":["dôverník","zmocnenec"],"pol":["pełnomocnik","plenipotent","powiernik","przedstawiciel"],"slv":["upravitelj"],"ita":["fiduciario"],"ron":["custode"],"fin":["omaisuuden hoitaja","uskottu mies"],"lit":["patikėtinis"]},"links":[{"link_type":"W3C","target":"http://www.w3.org/2006/03/wn/wn20/instances/synset-fiduciary-noun-1"}]}]