[{"definition":"someone who makes patterns (as for sewing or carpentry or metalworking)","examples":[],"lemmas":[{"lemma":"patternmaker","language":"en","forms":[],"sense_key":"patternmaker%1:18:00::","subcats":[],"importance":1}],"id":"10428554-n","ili":"i91911","pos":"n","subject":"noun.person","relations":[{"src_word":null,"trg_word":null,"rel_type":"hypernym","target":"10303761-n"}],"old_keys":{"pwn17":["08341888-n"],"pwn21":["10253466-n"],"pwn15":["06252379-n"],"pwn20":["09733800-n"],"pwn30":["10408809-n"],"pwn171":["08530240-n"],"pwn16":["07463354-n"]},"gloss":null,"foreign":{"fin":["malliseppä"],"tha":["ช่างเขียนลาย","ช่างแกะลาย"],"ita":["modellista"]},"links":[{"link_type":"W3C","target":"http://www.w3.org/2006/03/wn/wn20/instances/synset-patternmaker-noun-1"}]}]