[{"definition":"a blond whose hair is bleached with peroxide","examples":[],"lemmas":[{"lemma":"peroxide blond","language":"en","forms":[],"sense_key":"peroxide_blond%1:18:00::","subcats":[],"importance":1},{"lemma":"peroxide blonde","language":"en","forms":[],"sense_key":"peroxide_blonde%1:18:00::","subcats":[],"importance":1}],"id":"10436790-n","ili":"i91959","pos":"n","subject":"noun.person","relations":[{"src_word":null,"trg_word":null,"rel_type":"hypernym","target":"09879912-n"}],"old_keys":{"pwn171":["08537517-n"],"pwn20":["09741776-n"],"pwn17":["08348982-n"],"pwn21":["10261660-n"],"pwn30":["10417045-n"]},"gloss":null,"foreign":{"fin":["peroksidiblondi","tekoblondi"]},"links":[{"link_type":"W3C","target":"http://www.w3.org/2006/03/wn/wn20/instances/synset-peroxide_blond-noun-1"}]}]