[{"definition":"British statesman who as Prime Minister pursued a policy of appeasement toward fascist Germany (1869-1940)","examples":[],"lemmas":[{"lemma":"Chamberlain","language":"en","forms":[],"sense_key":"chamberlain%1:18:02::","subcats":[],"importance":1},{"lemma":"Arthur Neville Chamberlain","language":"en","forms":[],"sense_key":"arthur_neville_chamberlain%1:18:00::","subcats":[],"importance":1},{"lemma":"Neville Chamberlain","language":"en","forms":[],"sense_key":"neville_chamberlain%1:18:00::","subcats":[],"importance":1}],"id":"10909441-n","ili":"i94684","pos":"n","subject":"noun.person","relations":[{"src_word":null,"trg_word":null,"rel_type":"instance_hypernym","target":"10669601-n"}],"old_keys":{"pwn171":["08912308-n"],"pwn17":["08708886-n"],"pwn30":["10889689-n"],"pwn20":["10181170-n"],"pwn21":["10728083-n"]},"gloss":null,"foreign":{"spa":["Neville Chamberlain"],"glg":["Neville Chamberlain"],"por":["Neville Chamberlain","Neville chamberlain"],"fra":["Arthur Neville Chamberlain","Chamberlain","chambellan"],"cat":["Neville Chamberlain"],"zsm":["Arthur Neville Chamberlain","Chamberlain","Neville Chamberlain"],"tha":["อาร์เธอร์ เนวิลล์ แชมเบอร์เลน","เนวิลล์ แชมเบอร์เลน","แชมเบอร์เลน"],"fin":["Arthur Neville Chamberlain","Chamberlain","Neville Chamberlain"],"ind":["Arthur Neville Chamberlain","Chamberlain","Neville Chamberlain"],"jpn":["チェンバレン"],"hrv":["Neville Chamberlain"]},"links":[{"link_type":"W3C","target":"http://www.w3.org/2006/03/wn/wn20/instances/synset-Chamberlain-noun-1"},{"link_type":"Wikipedia","target":"Neville_Chamberlain"}]}]